{
	"format_version": "1.12.0",
	"minecraft:geometry": [
		{
			"description": {
				"identifier": "geometry.unknown",
				"texture_width": 64,
				"texture_height": 64,
				"visible_bounds_width": 3,
				"visible_bounds_height": 3.5,
				"visible_bounds_offset": [0, 1.25, 0]
			},
			"bones": [
				{
					"name": "right_leg",
					"pivot": [-3, 4, 1],
					"cubes": [
						{"origin": [1, 0, -3], "size": [4, 5, 4], "pivot": [0, 0, 0], "rotation": [-180, 0, 180], "uv": [16, 33]}
					]
				},
				{
					"name": "left_leg",
					"pivot": [3, 4, 1],
					"cubes": [
						{"origin": [-5, 0, -3], "size": [4, 5, 4], "pivot": [0, 0, 0], "rotation": [-180, 0, 180], "uv": [0, 30]}
					]
				},
				{
					"name": "head",
					"pivot": [0, 5.8, -1],
					"cubes": [
						{"origin": [-6, 4, -7], "size": [12, 10, 12], "pivot": [0, 14, 0], "rotation": [-180, 0, 180], "uv": [0, 0]},
						{"origin": [-6, 14, 3], "size": [12, 2, 2], "pivot": [0, 0, 0], "rotation": [-180, 0, 180], "uv": [0, 26]},
						{"origin": [-6, 14, -7], "size": [12, 2, 2], "pivot": [0, 0, 0], "rotation": [-180, 0, 180], "uv": [0, 22]},
						{"origin": [-3, 14, 4], "size": [8, 2, 2], "pivot": [0, 0, 0], "rotation": [0, -90, 0], "uv": [34, 22]},
						{"origin": [-3, 14, -6], "size": [8, 2, 2], "pivot": [0, 0, 0], "rotation": [0, -90, 0], "uv": [28, 33]}
					]
				},
				{
					"name": "trunk",
					"pivot": [0, 5.8, -1],
					"cubes": [
						{"origin": [-1.36939, 7.00801, 5], "size": [3, 3, 6], "pivot": [0.13061, 0.00801, 0], "rotation": [-180, 0, 180], "uv": [22, 24]}
					]
				},
				{
					"name": "arrow",
					"pivot": [0, 6, -1],
					"rotation": [16.29261, 25.75026, 20.16313],
					"cubes": [
						{"origin": [-0.29272, 19.97712, 0.93319], "size": [1, 3, 0], "pivot": [5.07617, 13.48248, -0.79586], "rotation": [0, 0, 0], "uv": [10, 42]},
						{"origin": [-1.29272, 12.97712, 0.93319], "size": [1, 9, 0], "pivot": [5.07617, 13.48248, -0.79586], "rotation": [0, 0, 0], "uv": [2, 39]},
						{"origin": [-2.29272, 19.97712, 0.93319], "size": [1, 3, 0], "pivot": [5.07617, 13.48248, -0.79586], "rotation": [0, 0, 0], "uv": [42, 9]},
						{"origin": [7.30523, 19.97712, 5.07304], "size": [1, 3, 0], "pivot": [5.07617, 13.48248, -0.79586], "rotation": [0, -90, 0], "uv": [8, 42]},
						{"origin": [5.30523, 19.97712, 5.07304], "size": [1, 3, 0], "pivot": [5.07617, 13.48248, -0.79586], "rotation": [0, -90, 0], "uv": [42, 6]},
						{"origin": [6.30523, 12.97712, 5.07304], "size": [1, 9, 0], "pivot": [5.07617, 13.48248, -0.79586], "rotation": [0, -90, 0], "uv": [0, 39]}
					]
				},
				{
					"name": "arrow2",
					"pivot": [0.31601, 3.50012, -1.1975],
					"rotation": [12.07071, 3.42271, -14.60975],
					"cubes": [
						{"origin": [0.78871, 18.72399, 1.06761], "size": [1, 3, 0], "pivot": [5.40811, 12.14148, -0.88468], "rotation": [0, 0, 0], "uv": [6, 42]},
						{"origin": [-0.21129, 11.72399, 1.06761], "size": [1, 9, 0], "pivot": [5.40811, 12.14148, -0.88468], "rotation": [0, 0, 0], "uv": [38, 37]},
						{"origin": [-1.21129, 18.72399, 1.06761], "size": [1, 3, 0], "pivot": [5.40811, 12.14148, -0.88468], "rotation": [0, 0, 0], "uv": [4, 42]},
						{"origin": [7.86041, 18.72399, 4.23472], "size": [1, 3, 0], "pivot": [5.40811, 12.14148, -0.88468], "rotation": [0, -90, 0], "uv": [42, 3]},
						{"origin": [5.86041, 18.72399, 4.23472], "size": [1, 3, 0], "pivot": [5.40811, 12.14148, -0.88468], "rotation": [0, -90, 0], "uv": [42, 0]},
						{"origin": [6.86041, 11.72399, 4.23472], "size": [1, 9, 0], "pivot": [5.40811, 12.14148, -0.88468], "rotation": [0, -90, 0], "uv": [38, 0]}
					]
				},
				{
					"name": "arrow3",
					"pivot": [0, 6, -1],
					"rotation": [12.5, 0, 0],
					"cubes": [
						{"origin": [-1.5, 20.72817, 3.613], "size": [1, 3, 0], "pivot": [3, 14.16105, 1.6604], "rotation": [0, 0, 0], "uv": [40, 40]},
						{"origin": [-2.5, 11.72817, 3.613], "size": [1, 11, 0], "pivot": [3, 14.16105, 1.6604], "rotation": [0, 0, 0], "uv": [6, 0]},
						{"origin": [-3.5, 20.72817, 3.613], "size": [1, 3, 0], "pivot": [3, 14.16105, 1.6604], "rotation": [0, 0, 0], "uv": [40, 37]},
						{"origin": [5.45259, 20.72817, 6.6604], "size": [1, 3, 0], "pivot": [3, 14.16105, 1.6604], "rotation": [0, -90, 0], "uv": [40, 29]},
						{"origin": [3.45259, 20.72817, 6.6604], "size": [1, 3, 0], "pivot": [3, 14.16105, 1.6604], "rotation": [0, -90, 0], "uv": [40, 26]},
						{"origin": [4.45259, 11.72817, 6.6604], "size": [1, 11, 0], "pivot": [3, 14.16105, 1.6604], "rotation": [0, -90, 0], "uv": [4, 0]}
					]
				},
				{
					"name": "arrow4",
					"pivot": [0, 7, -1],
					"rotation": [0, 17.5, 0],
					"cubes": [
						{"origin": [-3.73283, 22.37324, 2.93914], "size": [1, 3, 0], "pivot": [1.30044, 15, 1.04802], "rotation": [-7.32417, -1.61888, -12.39638], "uv": [40, 9]},
						{"origin": [-4.73283, 15.37324, 2.93914], "size": [1, 9, 0], "pivot": [1.30044, 15, 1.04802], "rotation": [-7.32417, -1.61888, -12.39638], "uv": [36, 37]},
						{"origin": [-5.73283, 22.37324, 2.93914], "size": [1, 3, 0], "pivot": [1.30044, 15, 1.04802], "rotation": [-7.32417, -1.61888, -12.39638], "uv": [40, 6]},
						{"origin": [3.69155, 22.37324, 6.58129], "size": [1, 3, 0], "pivot": [1.30044, 15, 1.04802], "rotation": [-102.5, -82.5, 90], "uv": [40, 3]},
						{"origin": [1.69155, 22.37324, 6.58129], "size": [1, 3, 0], "pivot": [1.30044, 15, 1.04802], "rotation": [-102.5, -82.5, 90], "uv": [40, 0]},
						{"origin": [2.69155, 15.37324, 6.58129], "size": [1, 9, 0], "pivot": [1.30044, 15, 1.04802], "rotation": [-102.5, -82.5, 90], "uv": [34, 37]}
					]
				},
				{
					"name": "arrow5",
					"pivot": [0, 7, -1],
					"rotation": [2.56062, 12.48791, 8.05404],
					"cubes": [
						{"origin": [-2.23853, 19.29619, 4.1477], "size": [1, 3, 0], "pivot": [2.69394, 12.38343, 2.19696], "rotation": [0, 0, 0], "uv": [14, 39]},
						{"origin": [-3.23853, 14.29619, 4.1477], "size": [1, 7, 0], "pivot": [2.69394, 12.38343, 2.19696], "rotation": [0, 0, 0], "uv": [18, 30]},
						{"origin": [-4.23853, 19.29619, 4.1477], "size": [1, 3, 0], "pivot": [2.69394, 12.38343, 2.19696], "rotation": [0, 0, 0], "uv": [12, 39]},
						{"origin": [5.14467, 19.29619, 7.62943], "size": [1, 3, 0], "pivot": [2.69394, 12.38343, 2.19696], "rotation": [0, -90, 0], "uv": [10, 39]},
						{"origin": [3.14467, 19.29619, 7.62943], "size": [1, 3, 0], "pivot": [2.69394, 12.38343, 2.19696], "rotation": [0, -90, 0], "uv": [8, 39]},
						{"origin": [4.14467, 14.29619, 7.62943], "size": [1, 7, 0], "pivot": [2.69394, 12.38343, 2.19696], "rotation": [0, -90, 0], "uv": [16, 30]}
					]
				},
				{
					"name": "arrow6",
					"pivot": [0, 7, -1],
					"rotation": [-16.17354, 21.69365, 6.3809],
					"cubes": [
						{"origin": [0.86228, 22.14974, 0.68867], "size": [1, 3, 0], "pivot": [6.10157, 14.6321, -1.09613], "rotation": [0, 0, 0], "uv": [6, 39]},
						{"origin": [-0.13772, 14.14974, 0.68867], "size": [1, 10, 0], "pivot": [6.10157, 14.6321, -1.09613], "rotation": [0, 0, 0], "uv": [10, 0]},
						{"origin": [-1.13772, 22.14974, 0.68867], "size": [1, 3, 0], "pivot": [6.10157, 14.6321, -1.09613], "rotation": [0, 0, 0], "uv": [4, 39]},
						{"origin": [8.38637, 22.14974, 4.64316], "size": [1, 3, 0], "pivot": [6.10157, 14.6321, -1.09613], "rotation": [0, -90, 0], "uv": [38, 26]},
						{"origin": [6.38637, 22.14974, 4.64316], "size": [1, 3, 0], "pivot": [6.10157, 14.6321, -1.09613], "rotation": [0, -90, 0], "uv": [38, 9]},
						{"origin": [7.38637, 14.14974, 4.64316], "size": [1, 10, 0], "pivot": [6.10157, 14.6321, -1.09613], "rotation": [0, -90, 0], "uv": [8, 0]}
					]
				},
				{
					"name": "arrow7",
					"pivot": [0, 7, -1],
					"rotation": [1.40046, 42.54799, -3.90046],
					"cubes": [
						{"origin": [0.22112, 20.30646, 2.05118], "size": [1, 3, 0], "pivot": [6.07354, 13.34247, 0.5782], "rotation": [0, 0, 0], "uv": [36, 26]},
						{"origin": [-0.77888, 13.30646, 2.05118], "size": [1, 9, 0], "pivot": [6.07354, 13.34247, 0.5782], "rotation": [0, 0, 0], "uv": [32, 37]},
						{"origin": [-1.77888, 20.30646, 2.05118], "size": [1, 3, 0], "pivot": [6.07354, 13.34247, 0.5782], "rotation": [0, 0, 0], "uv": [36, 9]},
						{"origin": [8.04652, 20.30646, 6.93062], "size": [1, 3, 0], "pivot": [6.07354, 13.34247, 0.5782], "rotation": [0, -90, 0], "uv": [34, 26]},
						{"origin": [6.04652, 20.30646, 6.93062], "size": [1, 3, 0], "pivot": [6.07354, 13.34247, 0.5782], "rotation": [0, -90, 0], "uv": [20, 30]},
						{"origin": [7.04652, 13.30646, 6.93062], "size": [1, 9, 0], "pivot": [6.07354, 13.34247, 0.5782], "rotation": [0, -90, 0], "uv": [36, 0]}
					]
				},
				{
					"name": "arrow8",
					"pivot": [9, 4, 3],
					"rotation": [177.94473, 17.76123, -165.46141],
					"cubes": [
						{"origin": [13.01177, 20.64506, 7.3509], "size": [1, 3, 0], "pivot": [16.80848, 13.71563, 5.47997], "rotation": [175.92226, 0.80984, -157.54331], "uv": [14, 30]},
						{"origin": [12.01177, 11.64506, 7.3509], "size": [1, 11, 0], "pivot": [16.80848, 13.71563, 5.47997], "rotation": [175.92226, 0.80984, -157.54331], "uv": [2, 0]},
						{"origin": [11.01177, 20.64506, 7.3509], "size": [1, 3, 0], "pivot": [16.80848, 13.71563, 5.47997], "rotation": [175.92226, 0.80984, -157.54331], "uv": [12, 30]},
						{"origin": [19.17942, 20.64506, 9.77667], "size": [1, 3, 0], "pivot": [16.80848, 13.71563, 5.47997], "rotation": [78.75724, 85.84275, 101.24276], "uv": [2, 30]},
						{"origin": [17.17942, 20.64506, 9.77667], "size": [1, 3, 0], "pivot": [16.80848, 13.71563, 5.47997], "rotation": [78.75724, 85.84275, 101.24276], "uv": [0, 30]},
						{"origin": [18.17942, 11.64506, 9.77667], "size": [1, 11, 0], "pivot": [16.80848, 13.71563, 5.47997], "rotation": [78.75724, 85.84275, 101.24276], "uv": [0, 0]}
					]
				}
			]
		}
	]
}